pyvegh-0.8.0.dist-info/METADATA
pyvegh-0.8.0.dist-info/WHEEL
pyvegh-0.8.0.dist-info/entry_points.txt
pyvegh-0.8.0.dist-info/licenses/LICENSE
vegh/__init__.py
vegh/_core.abi3.so
vegh/analytics.py
vegh/cli.py
vegh/cli_commands.py
vegh/cli_config.py
vegh/cli_helpers.py
vegh/cli_hooks.py
vegh/cli_main.py
vegh/cli_repo.py
vegh/config.jsonc
vegh/jsonc.py
pyvegh-0.8.0.dist-info/RECORD
