Metadata-Version: 2.4
Name: pyvegh
Version: 0.8.0
Classifier: Programming Language :: Python :: 3.10
Classifier: Programming Language :: Python :: 3.11
Classifier: Programming Language :: Python :: 3.12
Classifier: Programming Language :: Python :: 3.13
Classifier: Programming Language :: Python :: 3.14
Classifier: Programming Language :: Python :: 3.15
Classifier: Programming Language :: Python :: 3 :: Only
Classifier: Programming Language :: Rust
Classifier: License :: OSI Approved :: MIT License
Classifier: Operating System :: OS Independent
Classifier: Topic :: Software Development :: Libraries
Classifier: Topic :: Utilities
Classifier: Intended Audience :: Developers
Classifier: Development Status :: 5 - Production/Stable
Requires-Dist: typer>=0.20.0
Requires-Dist: rich>=14.2.0
Requires-Dist: shellingham>=1.5.4
Requires-Dist: requests>=2.32.5
License-File: LICENSE
Summary: Python bindings for Vegh - The Snapshot Tool.
Keywords: snapshot,backup,rust,binding,loc,analytics
Author: CodeTease
Requires-Python: >=3.10
